{
  "k": 3,
  "tau": 450,
  "log_k": 1.0986122886681098,
  "results": [
    {
      "step": 100,
      "lambda_max": 4.538652420043945,
      "lambda_min": -0.000133514404296875,
      "ratio": 33993.72857142857,
      "loss": 2.861915111541748,
      "grad_norm": 0.33144062757492065,
      "iters_max": 26,
      "iters_min": 12,
      "time_s": 51.4,
      "phase": "PLATEAU"
    },
    {
      "step": 200,
      "lambda_max": 11.134171485900879,
      "lambda_min": -0.0010404586791992188,
      "ratio": 10701.21448212649,
      "loss": 2.6873719692230225,
      "grad_norm": 0.7895328402519226,
      "iters_max": 12,
      "iters_min": 12,
      "time_s": 33.4,
      "phase": "PLATEAU"
    },
    {
      "step": 300,
      "lambda_max": 13.829339981079102,
      "lambda_min": -0.0016613006591796875,
      "ratio": 8324.405281285879,
      "loss": 1.9803962707519531,
      "grad_norm": 1.2114381790161133,
      "iters_max": 12,
      "iters_min": 12,
      "time_s": 34.1,
      "phase": "PLATEAU"
    },
    {
      "step": 400,
      "lambda_max": 20.40753173828125,
      "lambda_min": -0.00093841552734375,
      "ratio": 21746.79674796748,
      "loss": 0.796393632888794,
      "grad_norm": 1.4930046796798706,
      "iters_max": 26,
      "iters_min": 12,
      "time_s": 50.8,
      "phase": "TRANS"
    },
    {
      "step": 500,
      "lambda_max": 16.403308868408203,
      "lambda_min": -0.003421783447265625,
      "ratio": 4793.789297658863,
      "loss": 0.15621373057365417,
      "grad_norm": 0.9318751096725464,
      "iters_max": 27,
      "iters_min": 12,
      "time_s": 51.8,
      "phase": "TRANS"
    },
    {
      "step": 900,
      "lambda_max": 0.4273968040943146,
      "lambda_min": 8.943676948547363e-05,
      "ratio": 4778.759413528824,
      "loss": 0.0016355899861082435,
      "grad_norm": 0.007164502516388893,
      "iters_max": 16,
      "iters_min": 12,
      "time_s": 37.9,
      "phase": "CONV"
    },
    {
      "step": 1300,
      "lambda_max": 0.23385408520698547,
      "lambda_min": 5.558133125305176e-05,
      "ratio": 4207.42144772118,
      "loss": 0.0008038553642109036,
      "grad_norm": 0.00352354790084064,
      "iters_max": 21,
      "iters_min": 12,
      "time_s": 23.9,
      "phase": "CONV"
    }
  ]
}